mcp_server_kubernetes/__init__.py
mcp_server_kubernetes/mcp_kubernetes.py
mcp_server_kubernetes-0.1.6.dist-info/METADATA
mcp_server_kubernetes-0.1.6.dist-info/WHEEL
mcp_server_kubernetes-0.1.6.dist-info/entry_points.txt
mcp_server_kubernetes-0.1.6.dist-info/top_level.txt
mcp_server_kubernetes-0.1.6.dist-info/RECORD
